Metadata-Version: 1.0
Name: adispatch
Version: 0.5.0
Summary: Multiple dispatch in function annotaions
Home-page: http://github.com/waipu/adispatch/
Author: UNKNOWN
Author-email: waipu@cirno.de
License: BSD
Keywords: dispatch
Platform: UNKNOWN
